features/__init__.py
features/feature_generation.py
features/feature_spec.py
features/hyper_feature.py
features/sql_gen.py
ben_mackenzie_features-0.0.17.dist-info/LICENSE
ben_mackenzie_features-0.0.17.dist-info/METADATA
ben_mackenzie_features-0.0.17.dist-info/WHEEL
ben_mackenzie_features-0.0.17.dist-info/top_level.txt
ben_mackenzie_features-0.0.17.dist-info/RECORD
