Metadata-Version: 2.1
Name: ben-mackenzie-features
Version: 0.0.17
Summary: A small example package
Author-email: Example Author <author@example.com>
Classifier: Programming Language :: Python :: 3
Classifier: License :: OSI Approved :: MIT License
Classifier: Operating System :: OS Independent
Requires-Python: >=3.7
License-File: LICENSE
Requires-Dist: python-dotenv
Requires-Dist: pyspark
Requires-Dist: databricks-feature-store
Requires-Dist: Jinja2
Requires-Dist: pandas
Requires-Dist: pyaml
